pygcap/__init__.py
pygcap/_accessory.py
pygcap/_blast.py
pygcap/_cluster.py
pygcap/_count.py
pygcap/_parse.py
pygcap/_probe.py
pygcap/_profile.py
pygcap/_search.py
pygcap/_seqlib.py
pygcap/_utils.py
pygcap/_visualize.py
pygcap/cli.py
pygcap/main.py
pygcap/data/probe_sample.tsv
pygcap-1.2.6.dist-info/METADATA
pygcap-1.2.6.dist-info/WHEEL
pygcap-1.2.6.dist-info/entry_points.txt
pygcap-1.2.6.dist-info/top_level.txt
pygcap-1.2.6.dist-info/RECORD
