Metadata-Version: 2.1
Name: pygcap
Version: 1.2.6
Summary: Python package for probe-based gene cluster finding in large microbial genome database
Home-page: https://github.com/CompSynBioLab-KoreaUniv/pyGCAP
Author: jsrim
Author-email: comfortindex@naver.com
Keywords: gene,cluster,genomics,bioinformatics
Classifier: Programming Language :: Python :: 3.6
Classifier: Programming Language :: Python :: 3.7
Classifier: Programming Language :: Python :: 3.8
Classifier: Programming Language :: Python :: 3.9
Classifier: Programming Language :: Python :: 3.10
Classifier: Programming Language :: Python :: 3.11
Requires-Python: >=3.6
Requires-Dist: pandas (>=2.1)
Requires-Dist: matplotlib (<3.9,>=3.7)
Requires-Dist: requests
Requires-Dist: setuptools
